unite_toolbox/__init__.py
unite_toolbox/bin_estimators.py
unite_toolbox/kde_estimators.py
unite_toolbox/knn_estimators.py
unite_toolbox/utils/__init__.py
unite_toolbox/utils/bootstrapping.py
unite_toolbox/utils/data_validation.py
unite_toolbox/utils/marginal_scores.py
unite_toolbox/utils/sampling.py
unite_toolbox-0.2.1.dist-info/WHEEL
unite_toolbox-0.2.1.dist-info/METADATA
unite_toolbox-0.2.1.dist-info/RECORD
