Metadata-Version: 2.3
Name: unite-toolbox
Version: 0.2.1
Summary: A toolbox for practical applications of information theory.
Author: Manuel Álvarez Chaves, Uwe Ehret
Author-email: Manuel Álvarez Chaves <manuel.alvarezchaves@simtech.uni-stuttgart.de>, Uwe Ehret <uwe.ehret@kit.edu>
License: MIT License
Requires-Dist: coverage>=7.10.3
Requires-Dist: numpy>=1.25.2
Requires-Dist: scipy>=1.12.0
Requires-Dist: tqdm>=4.66.6
Maintainer: Manuel Álvarez Chaves
Maintainer-email: Manuel Álvarez Chaves <manuel.alvarezchaves@simtech.uni-stuttgart.de>
Requires-Python: >=3.10
Project-URL: Documentation, https://unite-toolbox.readthedocs.io/
Project-URL: Repository, https://github.com/manuel-alvarez-chaves/unite_toolbox
Project-URL: Team, https://www.simtech.uni-stuttgart.de/exc/research/junior-research-groups/statistical-model-data-integration/
